ussf_discordbot_cogs/__init__.py
ussf_discordbot_cogs/auth_hooks.py
ussf_discordbot_cogs/helper.py
ussf_discordbot_cogs/cogs/about.py
ussf_discordbot_cogs/cogs/auth.py
ussf_discordbot_cogs/cogs/recruit_me.py
ussf_discordbot_cogs-0.0.4.dist-info/METADATA
ussf_discordbot_cogs-0.0.4.dist-info/WHEEL
ussf_discordbot_cogs-0.0.4.dist-info/RECORD
