Metadata-Version: 2.4
Name: ussf-discordbot-cogs
Version: 0.0.4
Summary: US-SF customized cogs for aa-discordbot
Project-URL: Changelog, https://github.com/aevans1987/us-sf-discordbot-cogs/blob/main/changelog.md
Project-URL: Documentation, https://github.com/aevans1987/us-sf-discordbot-cogs/blob/main/readme.md
Project-URL: Homepage, https://github.com/aevans1987/us-sf-discordbot-cogs
Project-URL: Source, https://github.com/aevans1987/us-sf-discordbot-cogs.git
Project-URL: Tracker, https://github.com/aevans1987/us-sf-discordbot-cogs/issues
Author-email: Andrew Evans <ade1987@pm.me>
Keywords: allianceauth,discord,eveonline,us_space_force
Classifier: Environment :: Web Environment
Classifier: Framework :: Django
Classifier: Framework :: Django :: 4.0
Classifier: Intended Audience :: Developers
Classifier: License :: OSI Approved :: GNU General Public License v3 (GPLv3)
Classifier: Operating System :: OS Independent
Classifier: Programming Language :: Python
Classifier: Programming Language :: Python :: 3 :: Only
Classifier: Programming Language :: Python :: 3.8
Classifier: Programming Language :: Python :: 3.9
Classifier: Programming Language :: Python :: 3.10
Classifier: Programming Language :: Python :: 3.11
Classifier: Programming Language :: Python :: 3.12
Classifier: Programming Language :: Python :: 3.13
Classifier: Topic :: Internet :: WWW/HTTP
Classifier: Topic :: Internet :: WWW/HTTP :: Dynamic Content
Requires-Python: >=3.8
Requires-Dist: allianceauth-app-utils>=1.14.1
Requires-Dist: allianceauth-discordbot
Requires-Dist: allianceauth<5,>=3
Requires-Dist: django-eveuniverse>=1.3
